[
  {
    "activity_date": "2026-03-02",
    "prev_registered": 88775861,
    "registered": 87985493,
    "prev_eligible": 268789512,
    "eligible": 267188344,
    "prev_combined": 357565373,
    "combined": 355173837
  },
  {
    "activity_date": "2026-03-03",
    "prev_registered": 87985493,
    "registered": 87143495,
    "prev_eligible": 267188344,
    "eligible": 265076376,
    "prev_combined": 355173837,
    "combined": 352219872
  },
  {
    "activity_date": "2026-03-05",
    "prev_registered": 81235306,
    "registered": 81733733,
    "prev_eligible": 270106619,
    "eligible": 267412161,
    "prev_combined": 351341925,
    "combined": 349145895
  },
  {
    "activity_date": "2026-03-06",
    "prev_registered": 81733733,
    "registered": 79988594,
    "prev_eligible": 267412161,
    "eligible": 266299378,
    "prev_combined": 349145895,
    "combined": 346287972
  },
  {
    "activity_date": "2026-03-09",
    "prev_registered": 79988594,
    "registered": 78483968,
    "prev_eligible": 266299378,
    "eligible": 266826475,
    "prev_combined": 346287972,
    "combined": 345310443
  }
]